sudokutils-1.1.1b1.dist-info/METADATA
sudokutils-1.1.1b1.dist-info/WHEEL
sudokutils-1.1.1b1.dist-info/license_files/LICENSE.md
sudokutils/__init__.py
sudokutils/__init__.pyi
sudokutils/py.typed
sudokutils/sudokutils.pyd
sudokutils-1.1.1b1.dist-info/RECORD
