Metadata-Version: 2.1
Name: sudokutils
Version: 1.1.1b1
Classifier: Development Status :: 4 - Beta
Classifier: Programming Language :: Python
License-File: LICENSE.md
Summary: Utilities for working with sudokus
Keywords: sudoku,utilities,rust
Author-email: wookie184 <wookie1840@gmail.com>
Maintainer-email: wookie184 <wookie1840@gmail.com>
Requires-Python: >=3.8
Project-URL: repository, https://github.com/wookie184/rust-sudoku
Project-URL: homepage, https://github.com/wookie184/rust-sudoku
